souvenir/__init__.py
souvenir/image.py
souvenir/zipcode.py
souvenir_sv-2.1.5.dist-info/LICENSE
souvenir_sv-2.1.5.dist-info/WHEEL
souvenir_sv-2.1.5.dist-info/METADATA
souvenir_sv-2.1.5.dist-info/RECORD
