Metadata-Version: 2.1
Name: souvenir-sv
Version: 2.1.5
Summary: A package to get zipcodes from El Salvador departments
Author-email: standoge <stanlydoge@gmail.com>
Classifier: License :: OSI Approved :: GNU General Public License v3 or later (GPLv3+)
Requires-Dist: requests == 2.31.0
Requires-Dist: beautifulsoup4 == 4.11.1
Requires-Dist: bing-image-urls==0.1.5
Requires-Dist: google-search-results==2.4.1
Requires-Dist: requests-cache==1.0.1
Project-URL: Home, https://github.com/standoge/souvenir-sv
